README.md
setup.py
hhk_utils/__init__.py
hhk_utils/algorithm.py
hhk_utils/dataproc.py
hhk_utils.egg-info/PKG-INFO
hhk_utils.egg-info/SOURCES.txt
hhk_utils.egg-info/dependency_links.txt
hhk_utils.egg-info/entry_points.txt
hhk_utils.egg-info/top_level.txt