Metadata-Version: 1.0
Name: hhk-utils
Version: 0.0.2
Summary: for easy working
Home-page: https://github.com/hector-han/hhk-utils
Author: hhk
Author-email: hengke.han@outlook.com
License: UNKNOWN
Platform: UNKNOWN
